get_vat_eu/__init__.py
get_vat_eu/api.py
get_vat_eu/constants.py
get_vat_eu/exceptions.py
get_vat_eu-1.0.1.dist-info/DESCRIPTION.rst
get_vat_eu-1.0.1.dist-info/METADATA
get_vat_eu-1.0.1.dist-info/RECORD
get_vat_eu-1.0.1.dist-info/WHEEL
get_vat_eu-1.0.1.dist-info/entry_points.txt
get_vat_eu-1.0.1.dist-info/metadata.json
get_vat_eu-1.0.1.dist-info/top_level.txt
