Metadata-Version: 2.0
Name: get-vat-eu
Version: 1.0.1
Summary: A utility that is able to get and parse EU EC VATs.
Home-page: https://github.com/citycommerce/get-vat-eu
Author: CityCommerce srl
Author-email: citycommercedev@gmail.com
License: MIT
Keywords: vat ec eu
Platform: UNKNOWN
Classifier: Development Status :: 3 - Alpha
Classifier: Topic :: Utilities
Classifier: Intended Audience :: End Users/Desktop
Classifier: Environment :: Console
Classifier: License :: OSI Approved :: MIT License
Classifier: Programming Language :: Python :: 3
Requires-Python: >=3.5, <4
Requires-Dist: zeep (==3)
